pyoinformatics/__init__.py
pyoinformatics/align.py
pyoinformatics/io.py
pyoinformatics/seq.py
tests/__init__.py
tests/test_align.py
tests/test_seq.py
pyoinformatics-0.2.5.dist-info/LICENSE
pyoinformatics-0.2.5.dist-info/METADATA
pyoinformatics-0.2.5.dist-info/WHEEL
pyoinformatics-0.2.5.dist-info/top_level.txt
pyoinformatics-0.2.5.dist-info/RECORD
