Metadata-Version: 2.1
Name: pyoinformatics
Version: 0.2.5
Summary: A simple bioinformatics package
Home-page: https://github.com/Wytamma/pyoinformatics
Author: Wytamma Wirth
Author-email: wytamma.wirth@me.com
License: UNKNOWN
Platform: UNKNOWN
Classifier: Programming Language :: Python :: 3
Classifier: License :: OSI Approved :: MIT License
Classifier: Operating System :: OS Independent
Requires-Python: >=3.7
